sicor/__init__.py
sicor/sicor.py
sicor/sicor_ac.py
sicor/sicor_enmap.py
sicor/sicor_enmap_old.py
sicor/version.py
sicor/AC/ACG.py
sicor/AC/RtFo.py
sicor/AC/RtFo_3_phases.py
sicor/AC/__init__.py
sicor/AC/data/EnMAP_LUT_MOD5_formatted_1nm
sicor/AC/data/k_liquid_water_ice.xlsx
sicor/AC/data/newkur_EnMAP.dat
sicor/AC/data/solar_irradiances_400_2500_1.dill
sicor/ECMWF/ECMWF.py
sicor/ECMWF/__init__.py
sicor/Mask/Mask.py
sicor/Mask/__init__.py
sicor/Tools/SolarIrradiance.py
sicor/Tools/Tools.py
sicor/Tools/__init__.py
sicor/Tools/get_memory_use.py
sicor/Tools/inpaint.py
sicor/Tools/linear_error_moddeling.py
sicor/Tools/majority_mask_filter.py
sicor/Tools/ram.py
sicor/Tools/rsf_functions.py
sicor/Tools/sharedndarray.py
sicor/Tools/tqdm_joblist.py
sicor/Tools/EnMAP/LUT.py
sicor/Tools/EnMAP/__init__.py
sicor/Tools/EnMAP/conversion.py
sicor/Tools/EnMAP/metadata.py
sicor/Tools/EnMAP/multiprocessing.py
sicor/Tools/EnMAP/optimal_estimation.py
sicor/Tools/EnMAP/segmentation.py
sicor/Tools/NM/__init__.py
sicor/Tools/NM/c_digitize.pyx
sicor/Tools/NM/interp_spectral_n_1.py
sicor/Tools/NM/interp_spectral_n_10.py
sicor/Tools/NM/interp_spectral_n_11.py
sicor/Tools/NM/interp_spectral_n_12.py
sicor/Tools/NM/interp_spectral_n_13.py
sicor/Tools/NM/interp_spectral_n_14.py
sicor/Tools/NM/interp_spectral_n_2.py
sicor/Tools/NM/interp_spectral_n_3.py
sicor/Tools/NM/interp_spectral_n_4.py
sicor/Tools/NM/interp_spectral_n_5.py
sicor/Tools/NM/interp_spectral_n_6.py
sicor/Tools/NM/interp_spectral_n_7.py
sicor/Tools/NM/interp_spectral_n_8.py
sicor/Tools/NM/interp_spectral_n_9.py
sicor/Tools/NM/interp_spectral_n_template.pybak
sicor/Tools/NM/interpolate_n.py
sicor/Tools/cB/CloudMask.py
sicor/Tools/cB/__init__.py
sicor/Tools/cB/cB.py
sicor/Tools/cB/classical_bayesian.py
sicor/Tools/cB/data/cld_mask_20160321_s2.h5
sicor/Tools/data/Earth_Sun_distances_per_day_edited.csv
sicor/Tools/data/SUNp1fontenla.asc
sicor/Tools/data/Solar_irradiance_Thuillier_2002.xls
sicor/options/__init__.py
sicor-0.14.2.4.dist-info/AUTHORS.rst
sicor-0.14.2.4.dist-info/LICENSE
sicor-0.14.2.4.dist-info/METADATA
sicor-0.14.2.4.dist-info/WHEEL
sicor-0.14.2.4.dist-info/top_level.txt
sicor-0.14.2.4.dist-info/RECORD
