Metadata-Version: 2.1
Name: sicor
Version: 0.14.2.4
Summary: Sensor Independent Atmospheric Correction
Home-page: https://gitext.gfz-potsdam.de/EnMAP/sicor
Author-email: nbohn@gfz-potsdam.de
License: GNU General Public License v3 (GPLv3)
Keywords: SICOR,EnMAP,EnMAP-Box,hyperspectral,remote sensing,satellite,atmospheric correction
Platform: UNKNOWN
Classifier: Development Status :: 4 - Beta
Classifier: License :: OSI Approved :: GNU General Public License v3 (GPLv3)
Classifier: Natural Language :: English
Classifier: Programming Language :: Python :: 3.6
Classifier: Programming Language :: Python :: 3.7
Classifier: Programming Language :: Python :: 3.8
Requires-Dist: scikit-image
Requires-Dist: glymur
Requires-Dist: pyprind
Requires-Dist: geopandas
Requires-Dist: dicttoxml
Requires-Dist: tables
Requires-Dist: pandas
Requires-Dist: xlrd
Requires-Dist: psutil
Requires-Dist: sympy
Requires-Dist: pyproj
Requires-Dist: cerberus
Requires-Dist: scipy
Requires-Dist: tqdm
Requires-Dist: dill
Requires-Dist: shapely
Requires-Dist: geoarray
Requires-Dist: mpld3
Requires-Dist: jsmin
Requires-Dist: iso8601
Requires-Dist: pint
Requires-Dist: matplotlib
Requires-Dist: sphinx-argparse
Requires-Dist: numpy
Requires-Dist: pillow
Requires-Dist: pylint
Requires-Dist: mypy
Requires-Dist: pycodestyle
Requires-Dist: pydocstyle
Requires-Dist: flake8
Requires-Dist: sphinx
Requires-Dist: arosics
Requires-Dist: numba
Requires-Dist: netCDF4
Requires-Dist: pyrsr
